gemini_sre/__init__.py
gemini_sre/async_client.py
gemini_sre/client.py
gemini_sre/core/__init__.py
gemini_sre/core/circuit_breaker.py
gemini_sre/core/deduplication.py
gemini_sre/core/logging.py
gemini_sre/core/monitoring.py
gemini_sre/core/retry.py
gemini_sre/core/streaming.py
gemini_sre/proxies/__init__.py
gemini_sre/proxies/async_caches.py
gemini_sre/proxies/async_chats.py
gemini_sre/proxies/async_files.py
gemini_sre/proxies/async_models.py
gemini_sre/proxies/async_operations.py
gemini_sre/proxies/async_tunings.py
gemini_sre/proxies/caches.py
gemini_sre/proxies/chats.py
gemini_sre/proxies/files.py
gemini_sre/proxies/models.py
gemini_sre/proxies/operations.py
gemini_sre/proxies/tunings.py
gemini_sre-0.1.0.dist-info/licenses/LICENSE
gemini_sre-0.1.0.dist-info/licenses/LICENSE_GUIDE.md
gemini_sre-0.1.0.dist-info/METADATA
gemini_sre-0.1.0.dist-info/WHEEL
gemini_sre-0.1.0.dist-info/top_level.txt
gemini_sre-0.1.0.dist-info/RECORD
