Metadata-Version: 2.4
Name: gemini-sre
Version: 0.1.0
Summary: Example of Production-ready Google Gemini API wrapper with SRE features
Author: Giorgio C
License-Expression: MIT
Project-URL: Homepage, https://github.com/miticojo/gemini-sre-client
Project-URL: Documentation, https://github.com/miticojo/gemini-sre-client/blob/main/README.md
Project-URL: Repository, https://github.com/miticojo/gemini-sre-client
Project-URL: Issues, https://github.com/miticojo/gemini-sre-client/issues
Keywords: gemini,google,ai,llm,sre,reliability,monitoring,retry,circuit-breaker
Classifier: Development Status :: 3 - Alpha
Classifier: Intended Audience :: Developers
Classifier: Programming Language :: Python :: 3
Classifier: Programming Language :: Python :: 3.9
Classifier: Programming Language :: Python :: 3.10
Classifier: Programming Language :: Python :: 3.11
Classifier: Programming Language :: Python :: 3.12
Requires-Python: >=3.9
License-File: LICENSE
License-File: LICENSE_GUIDE.md
Requires-Dist: google-genai>=1.56.0
Requires-Dist: google-cloud-monitoring>=2.27.0
Requires-Dist: google-cloud-logging>=3.12.0
Requires-Dist: pydantic<3.0.0,>=2.12.0
Provides-Extra: dev
Requires-Dist: pytest>=7.0.0; extra == "dev"
Requires-Dist: pytest-cov>=4.0.0; extra == "dev"
Requires-Dist: pytest-asyncio>=0.21.0; extra == "dev"
Requires-Dist: pytest-mock>=3.15.1; extra == "dev"
Requires-Dist: black>=23.0.0; extra == "dev"
Requires-Dist: isort>=5.13.2; extra == "dev"
Requires-Dist: ruff>=0.8.4; extra == "dev"
Requires-Dist: mypy>=1.0.0; extra == "dev"
Requires-Dist: bandit>=1.7.10; extra == "dev"
Requires-Dist: pre-commit>=4.0.0; extra == "dev"
Provides-Extra: dashboards
Requires-Dist: google-cloud-monitoring-dashboards>=2.18.0; extra == "dashboards"
Dynamic: license-file
